pymathutilslib/__init__.py
pymathutilslib/utilidade1.py
pymathutilslib/utilidade2.py
pymathutilslib/other/__init__.py
pymathutilslib/other/utilidade3.py
pymathutilslib/other/utilidade4.py
pymathutilslib-0.0.2.dist-info/LICENCE
pymathutilslib-0.0.2.dist-info/METADATA
pymathutilslib-0.0.2.dist-info/WHEEL
pymathutilslib-0.0.2.dist-info/top_level.txt
pymathutilslib-0.0.2.dist-info/RECORD
