Metadata-Version: 2.1
Name: pymathutilslib
Version: 0.0.2
Summary: Teste de como criar um modulo python
Author: Ismael Nascimento
Author-email: ismaelnjr@icloud.com.br
License: MIT License
Keywords: module example
License-File: LICENCE
